xctools_mcp_server.py
mseep_xctools_mcp_server-0.1.2.dist-info/licenses/LICENSE
mseep_xctools_mcp_server-0.1.2.dist-info/METADATA
mseep_xctools_mcp_server-0.1.2.dist-info/WHEEL
mseep_xctools_mcp_server-0.1.2.dist-info/entry_points.txt
mseep_xctools_mcp_server-0.1.2.dist-info/top_level.txt
mseep_xctools_mcp_server-0.1.2.dist-info/RECORD
