Metadata-Version: 2.4
Name: mseep-xctools-mcp-server
Version: 0.1.2
Summary: A Model Context Protocol server for different Xcode related tools
Author-email: mseep <support@skydeck.ai>
Requires-Python: >=3.13
License-File: LICENSE
Requires-Dist: mcp[cli]>=1.2.0
Dynamic: license-file
